robox_sdk_lite/Logger.py
robox_sdk_lite/UdpSocket.py
robox_sdk_lite/__init__.py
robox_sdk_lite/roio_agent_mock.py
robox_sdk_lite/roio_client.py
robox_sdk_lite/roio_echo_client.py
robox_sdk_lite/roio_proto.py
robox_sdk_lite/roio_pub_meter.py
robox_sdk_lite/roio_sub_meter.py
robox_sdk_lite-1.1.0.dist-info/METADATA
robox_sdk_lite-1.1.0.dist-info/WHEEL
robox_sdk_lite-1.1.0.dist-info/licenses/LICENSE
robox_sdk_lite-1.1.0.dist-info/RECORD
