Metadata-Version: 2.4
Name: robox_sdk_lite
Version: 1.1.0
Summary: Robox SDK Lite for Intedigo RoIO Robot System
Project-URL: Homepage, https://github.com/PacoLijt/robox-sdk-lite
Project-URL: Bug Tracker, https://github.com/PacoLijt/robox-sdk-lite/issues
Author-email: Paco Li Junting <paco.li@intedigo.com>
License-File: LICENSE
Classifier: License :: OSI Approved :: Apache Software License
Classifier: Operating System :: OS Independent
Classifier: Programming Language :: Python :: 3
Requires-Python: >=3.10
